FunctionalUnit/Gauss.v
`ifndef GAUSS_UNIT_V
`define GAUSS_UNIT_V

//Author: Adán G. Medrano-Chávez
//This functional unit computes n(n+1)/2 through sums. It's silly, isn't it?
//Sorry Gauss

module Gauss(
  ctrlword,     //Manages register n, and acum as well as the output
  data,         //Input value
  status,       //Indicates whether the functional unit is available or not
  result,       //n(n+1)/2
  prediction,   //Indictes the datapath is processing the last element
  done,         //Indicates the job is done
  preset,
  clk           //Clock signal
);

  //This parameter defines the width of the operand and the result
  parameter width = 16;

  input wire[2:0] ctrlword; //control bits are dec_n, load_acum, init
  input wire[width-1:0] data; //input value
  input wire preset, clk;
  output reg status, prediction;
  output wire done;
  output wire[width-1:0] result;

  //Internal register storing the value of the variables.
  reg[width-1:0] n, acum;

  //Here the behavior of register is described according to the control word.
  //The case corresponding to state three needs 'n' tri-state buffers, so it's
  //described in a generate block
  always @(posedge clk) begin
    if (preset) begin
      n <= 0;
      acum <= 0;
    end
    else
      case (ctrlword)
        3'b001:  begin
                    n <= data;
                    acum <= 0;
                  end
        3'b010: acum <= acum + n;
        3'b100: n <= n - 1;
      endcase
  end

  always @(posedge clk) begin
    if ((ctrlword[1]) && (n==1))
      prediction = 1;
    else
      prediction = 0;
  end

  //Here the combinational blocks of the Gauss are described. The actual
  //inputs modifying the output of this block are only registers i and n as well
  //as the most significant bit of the control word
  always @(n) begin
    if (n > 0)
      status = 1; //HIGH means the datapath is working
    else
      status = 0; //LOW means the datapath is available
  end

  assign result = acum;
  assign done = ~|n;

endmodule // Gauss

`endif

FunctionalUnit/GaussControlUnit.v
`ifndef GAUSS_CONTROL_UNIT
`define GAUSS_CONTROL_UNIT

module GaussControlUnit(
  status,   //Signal indicating the job is done
  ctrlword, //Signals managing the Gauss datapath
  preset,   //Set the FSM in the init state
  clk       //Clock signal
);

  input wire preset, clk;
  input wire[1:0] status; //ready, status
  output wire[2:0] ctrlword;

  wire[2:0] nextstate;
  reg[2:0] state;

  //Nextstate logic
  assign nextstate[0] = ~status[0] | state[0]&(~status[0]) | state[2]&~status[0];
  assign nextstate[1] = status[1] & (state[0]&status[0] | state[2]&status[0]);
  assign nextstate[2] = status[1] & state[1];

  //Memory
  always @(posedge clk) begin
    if (preset)
      state <= 3'b001;
    else
      state <= nextstate;
  end

  //Output logic
  assign ctrlword = state;

endmodule // GaussControlUnit

`endif

FetchUnit/Dispatcher.v
`ifndef DISPATCHER_V
`define DISPATCHER_V

//Author: Adán G. Medrano-Chávez
//This module is a combinational logic block routing operands to an available
//functional unit. Besides, it emits a signal indicating which operand is the
//greatest in order to predict which datapointer ought to be updated

module Dispatcher(
  data0,      //Data pointed by dp0
  data1,      //Data pointed by dp1
  operand0,   //Conveys the operand the FU0 process
  operand1,   //Conveys the operand the FU process
  selpath,    //Signal routing data to an available datapath
  zer1,       //Indicates the data1 equals zero
  zer0,       //Indicates the data0 equals zero
  path1,      //Indicates the pointer that is being processed by fu0
  path0,      //Indicates the pointer that is being processed by fu1
  preset,     //Clears reg path
  clk         //Clock signal
);

  parameter width = 16; //data width

  input wire[width-1:0] data0, data1;
  input wire selpath, clk, preset;
  output wire path0, path1, zer0, zer1;
  output reg[width-1:0] operand0, operand1;

  reg path;

  //Behavioral description of two muxes
  always @(*) begin
    if (selpath) begin
      operand0 = data1;
      operand1 = data0;
    end
    else begin
      operand0 = data0;
      operand1 = data1;
    end
  end

  always @(posedge clk) begin
    if (preset)
      path <= 0;
    else
      path <= selpath;
  end

  assign zer0 = (data0 == 0) ? 1 : 0;
  assign zer1 = (data1 == 0) ? 1 : 0;
  assign path0 = path;
  assign path1 = ~path;


endmodule // Dispatcher

`endif

FetchUnit/DataMemory.v
`ifndef DATAMEMORY_V
`define DATAMEMORY_V

//Author: Adán G. Medrano-Chávez
//Memory able to address two data at the same time. This feature is needed to
//concurrently load two registers, namely R0 and R1, whose value is the operand
//of the two functional units that computes the sum of n
//This memory reads its content from a file

module DataMemory(
  addr1,  //address of the second operand
  addr0,  //addres of the first operand
  data1,  //value of the second operand
  data0   //value of the first operand  
);

  parameter wordsize = 16; //the word size
  parameter addrsize = 5; //the address size
  localparam memdepth = $pow(2, addrsize); //the memory depth

  //buses conveying the operand addresses
  input wire[addrsize-1:0] addr0, addr1;
  //buses conveying the operands to be processed
  output wire[wordsize-1:0] data0, data1;

  //memory storing the values to be processed
  reg[wordsize-1:0] memory[memdepth:0];

  //This initial block initializes the memory with the data stored in data.list
  initial begin
    //$readmemh(filename, mem_array, start_addr, stop_addr);
    //The last two value are optional arguments
    $readmemh("./FetchUnit/data.list", memory, 0, 31);
  end

  assign data1 = memory[addr1];
  assign data0 = memory[addr0];

endmodule // DataMemory

`endif

FetchUnit/DataFetch.v
`ifndef DATA_FETCH_V
`define DATA_FETCH_V

//Author: Adán G. Medrano-Chávez
//This module fetchs two values in the data memory. This task is accomplished
//by updating two pointers, namely dp0 and dp1, according the greatest address
//between them. A base pointer stores the greatest value

module FetchUnit(
  ctrlword, //Set of signals managing the registers and muxes of this module
  addr0,    //First operand address
  addr1,    //Second operand address
  ready,    //Indicates the registers have valid pointers
  preset,   //Sets dp0 and dp1 in their initial states
  clk       //Clock signal
);

  parameter addrsize = 5; //addrsize of operands
  //loadDP1, loadDP0, selMUXDP1
  input wire[2:0] ctrlword;
  input wire preset, clk;
  output wire ready;
  output wire[addrsize-1:0] addr0, addr1;

  //This signal is asserted when the address kept in dp0 is greater than dp1's
  reg selmuxbp; 

  //dp0 means data pointer 0
  //dp1 means data pointer 1
  //bp means base pointer, it keeps the greatest address between dp0 and dp1
  //Such direction is used to compute the 
  reg[addrsize-1:0] dp0, dp1, bp;

  //Behavioral description of the fetch unit
  //Both sequential and combinational elements are described here
  always@(posedge clk) begin
    if (preset) begin //If preset
      dp0 <= 0;
      dp1 <= 1;
      bp <= 1;
    end
    else begin
      if (ctrlword[2])  //load dp1
        dp1 <= (ctrlword[0]) ? bp + 2 : bp + 1;
      if (ctrlword[1])  //load dp0
        dp0 <= bp + 1;
    end 
  end

  //Base pointer is loaded when the negative edge of clk ocurrs
  always@(negedge clk)
    bp <= (selmuxbp) ? dp0 : dp1;

  always@(dp0 or dp1) begin
    if (dp0 > dp1)
      selmuxbp = 1;
    else
      selmuxbp = 0;
  end

  //The output of the module is described here

  assign addr0 = dp0;
  assign addr1 = dp1;
  assign ready = (dp1 > 0) ? 1 : 0;

endmodule // FetchUnit

`endif

FetchUnit/DataControlUnit.v
`ifndef DATA_CONTROL_UNIT
`define DATA_CONTROL_UNIT

//Author: Adán G. Medrano-Chávez
//This module manages the operation of the data fetch unit

module DataControlUnit(
  status,   //Processor status
  ctrlword, //Signals that manage the fetch unit
  preset,   //Set the FSM in its initial state
  clk       //Clock signal
);

  input wire[5:0] status; //zer1, zer0, pre1, pre0, path1, path0
  input wire preset, clk;

  //loaddp1, loaddp0, selmuxdp1, seldatapath
  output reg[3:0] ctrlword;

  
  wire[1:0] nextstate; //Nextstate logic input
  reg[1:0] state; //FSM Memory

  //Next state logic description
  assign nextstate[0] = ~(status[5] | status[4] | status[3] | status[2]);
  assign nextstate[1] = status[5] | status[4] | status[3] | status[2];

  //Memory Behavioral
  always @(posedge clk) begin
    if (preset)
      state <= 2'b01;
    else
      state <= nextstate;
  end

  //Output combinational logic
  always @(state or status) begin
    case ({state,status})
      //Non zero has been read
      8'b10_00_00_01 :	ctrlword = 5'b0000;
      8'b10_00_00_10 :	ctrlword = 5'b0000;
      8'b10_00_01_01 :	ctrlword = 5'b1001;
      8'b10_00_01_10 :	ctrlword = 5'b0100;
      8'b10_00_10_01 :	ctrlword = 5'b0101;
      8'b10_00_10_10 :	ctrlword = 5'b1000;
      8'b10_00_11_01 :	ctrlword = 5'b1110;
      8'b10_00_11_10 :	ctrlword = 5'b1110;
      //Read a zero in data0
      8'b10_01_00_01 :	ctrlword = 5'b0101;
      8'b10_01_00_10 :	ctrlword = 5'b0100;
      8'b10_01_01_01 :	ctrlword = 5'b1110;
      8'b10_01_01_10 :	ctrlword = 5'b0100;
      8'b10_01_10_01 :	ctrlword = 5'b0101;
      8'b10_01_10_10 :	ctrlword = 5'b1110;
      8'b10_01_11_01 :	ctrlword = 5'b1110;
      8'b10_01_11_10 :	ctrlword = 5'b1110;
      //Read a zero in data1
      8'b10_10_00_01 :	ctrlword = 5'b1001;
      8'b10_10_00_10 :	ctrlword = 5'b1000;
      8'b10_10_01_01 :	ctrlword = 5'b1001;
      8'b10_10_01_10 :	ctrlword = 5'b1110;
      8'b10_10_10_01 :	ctrlword = 5'b1110;
      8'b10_10_10_10 :	ctrlword = 5'b1000;
      8'b10_10_11_01 :	ctrlword = 5'b1110;
      8'b10_10_11_10 :  ctrlword = 5'b1110;
      8'b10_00_00_01 :  ctrlword = 5'b1110;
      //Read two zeroes
      8'b10_11_00_01 :  ctrlword = 5'b1110;
      8'b10_11_00_10 :  ctrlword = 5'b1110;
      8'b10_11_01_01 :  ctrlword = 5'b1110;
      8'b10_11_01_10 :  ctrlword = 5'b1110;
      8'b10_11_10_01 :  ctrlword = 5'b1110;
      8'b10_11_10_10 :  ctrlword = 5'b1110;
      8'b10_11_11_01 :  ctrlword = 5'b1110;
      8'b10_11_11_10 :  ctrlword = 5'b1110;
      default: ctrlword = 5'b00000;
    endcase
  end

endmodule // DataControlUnit

`endif

Processor.v
`ifndef PROCESSOR_V
`define PROCESSOR_V

`include "FetchUnit/DataFetch.v"
`include "FetchUnit/DataMemory.v"
`include "FetchUnit/Dispatcher.v"
`include "FetchUnit/DataControlUnit.v"
`include "FunctionalUnit/Gauss.v"
`include "FunctionalUnit/GaussControlUnit.v"

module Processor(
  done,
  preset,
  clk
);

  input wire preset, clk;
  output wire[1:0] done;

  wire[2:0] ctrlword_g0, ctrlword_g1;
  wire[3:0] ctrlword_d;
  wire[4:0] addr0, addr1;
  //ready, status1, status2, zer1, zer0, pre1, pre0, path1, path0
  wire[8:0] proc_status;
  wire[15:0] data0, data1, operand0, operand1, res0, res1;

  DataControlUnit ctrl_d0(
    proc_status[5:0], //Processor status
    ctrlword_d,       //Signals that manage the fetch unit
    preset,           //Set the FSM in its initial state
    clk               //Clock signal
  );

  FetchUnit fetch_u(
    ctrlword_d[3:1],      //Manages the registers and muxes of this module
    addr0,                //First operand address
    addr1,                //Second operand address
    proc_status[8],       //Indicates the registers have valid pointers
    preset,               //Sets dp0 and dp1 in their initial states
    ~clk                  //Clock signal
  );

  DataMemory data_mem(
    addr1,  //address of the second operand
    addr0,  //addres of the first operand
    data1,  //value of the second operand
    data0   //value of the first operand  
  );

  Dispatcher dispatcher_u(
    data0,          //Data pointed by dp0
    data1,          //Data pointed by dp1
    operand0,       //Conveys the operand the FU0 process
    operand1,       //Conveys the operand the FU process
    ctrlword_d[0],  //Signal routing data to an available datapath
    proc_status[5], //Indicates the data1 equals zero
    proc_status[4], //Indicates the data0 equals zero
    proc_status[1], //Indicates the pointer that is being processed by fu0
    proc_status[0], //Indicates the pointer that is being processed by fu1
    preset,         //Clears reg path
    ~clk            //Clock signal
  );

  GaussControlUnit ctrl_g1(
    {proc_status[8], proc_status[7]},   //Signal indicating the job is done
    ctrlword_g1,      //Signals managing the Gauss datapath
    preset,           //Sets the FSM in the init state
    clk               //Clock signal
  );

  GaussControlUnit ctrl_g0(
    {proc_status[8], proc_status[6]},   //Signal indicating the job is done
    ctrlword_g0,      //Signals managing the Gauss datapath
    preset,           //Sets the FSM in the init state
    clk               //Clock signal
  );

  Gauss functional_u1(
    ctrlword_g1,    //Manages register n, and acum as well as the output
    operand1,       //Input value
    proc_status[7], //Indicates whether the functional unit is available or not
    res1,           //n(n+1)/2
    proc_status[3], //Indictes the datapath is processing the last element
    done[1],        //Indicates the job is done
    preset,
    ~clk            //Clock signal
  );

  Gauss functional_u0(
    ctrlword_g0,    //Manages register n, and acum as well as the output
    operand0,       //Input value
    proc_status[6], //Indicates whether the functional unit is available or not
    res1,           //n(n+1)/2
    proc_status[2], //Indictes the datapath is processing the last element
    done[0],        //Indicates the job is done
    preset,
    ~clk            //Clock signal
  );

endmodule // Processor

`endif

Testbench.v
`include "Processor.v"
`timescale 1ns/100ps

module Testbench;

  wire[1:0] done;
  reg clk, preset;

  Processor proc_u(done, preset, clk);

  always #1 clk = ~clk;

  initial begin
    $dumpfile("processor.vcd");
    $dumpvars(0, Testbench);
    clk = 0;
    preset = 0;
    #0.5;
    preset = 1;
    #2;
    preset = 0;
    #20 $finish;
  end

endmodule // Testbench

processor.vcd
$date
	Wed Feb 15 14:08:17 2017
$end
$version
	Icarus Verilog
$end
$timescale
	100ps
$end
$scope module Testbench $end
$var wire 2 ! done [1:0] $end
$var reg 1 " clk $end
$var reg 1 # preset $end
$scope module proc_u $end
$var wire 1 " clk $end
$var wire 1 # preset $end
$var wire 16 $ res1 [15:0] $end
$var wire 9 % proc_status [8:0] $end
$var wire 16 & operand1 [15:0] $end
$var wire 16 ' operand0 [15:0] $end
$var wire 2 ( done [1:0] $end
$var wire 16 ) data1 [15:0] $end
$var wire 16 * data0 [15:0] $end
$var wire 3 + ctrlword_g1 [2:0] $end
$var wire 3 , ctrlword_g0 [2:0] $end
$var wire 4 - ctrlword_d [3:0] $end
$var wire 5 . addr1 [4:0] $end
$var wire 5 / addr0 [4:0] $end
$scope module ctrl_d0 $end
$var wire 1 " clk $end
$var wire 1 # preset $end
$var wire 6 0 status [5:0] $end
$var wire 2 1 nextstate [1:0] $end
$var reg 4 2 ctrlword [3:0] $end
$var reg 2 3 state [1:0] $end
$upscope $end
$scope module ctrl_g0 $end
$var wire 1 " clk $end
$var wire 3 4 ctrlword [2:0] $end
$var wire 1 # preset $end
$var wire 2 5 status [1:0] $end
$var wire 3 6 nextstate [2:0] $end
$var reg 3 7 state [2:0] $end
$upscope $end
$scope module ctrl_g1 $end
$var wire 1 " clk $end
$var wire 3 8 ctrlword [2:0] $end
$var wire 1 # preset $end
$var wire 2 9 status [1:0] $end
$var wire 3 : nextstate [2:0] $end
$var reg 3 ; state [2:0] $end
$upscope $end
$scope module data_mem $end
$var wire 16 < data0 [15:0] $end
$var wire 16 = data1 [15:0] $end
$var wire 5 > addr1 [4:0] $end
$var wire 5 ? addr0 [4:0] $end
$upscope $end
$scope module dispatcher_u $end
$var wire 1 @ clk $end
$var wire 16 A data0 [15:0] $end
$var wire 16 B data1 [15:0] $end
$var wire 1 C path0 $end
$var wire 1 D path1 $end
$var wire 1 # preset $end
$var wire 1 E selpath $end
$var wire 1 F zer1 $end
$var wire 1 G zer0 $end
$var reg 16 H operand0 [15:0] $end
$var reg 16 I operand1 [15:0] $end
$var reg 1 J path $end
$upscope $end
$scope module fetch_u $end
$var wire 5 K addr1 [4:0] $end
$var wire 1 L clk $end
$var wire 3 M ctrlword [2:0] $end
$var wire 1 # preset $end
$var wire 1 N ready $end
$var wire 5 O addr0 [4:0] $end
$var reg 5 P bp [4:0] $end
$var reg 5 Q dp0 [4:0] $end
$var reg 5 R dp1 [4:0] $end
$var reg 1 S selmuxbp $end
$upscope $end
$scope module functional_u0 $end
$var wire 1 T clk $end
$var wire 3 U ctrlword [2:0] $end
$var wire 16 V data [15:0] $end
$var wire 1 # preset $end
$var wire 16 W result [15:0] $end
$var wire 1 X done $end
$var reg 16 Y acum [15:0] $end
$var reg 16 Z n [15:0] $end
$var reg 1 [ prediction $end
$var reg 1 \ status $end
$upscope $end
$scope module functional_u1 $end
$var wire 1 ] clk $end
$var wire 3 ^ ctrlword [2:0] $end
$var wire 16 _ data [15:0] $end
$var wire 1 # preset $end
$var wire 16 ` result [15:0] $end
$var wire 1 a done $end
$var reg 16 b acum [15:0] $end
$var reg 16 c n [15:0] $end
$var reg 1 d prediction $end
$var reg 1 e status $end
$upscope $end
$upscope $end
$upscope $end
$enddefinitions $end
#0
$dumpvars
xe
0d
bx c
bx b
xa
bx `
bx _
bx ^
1]
x\
0[
bx Z
bx Y
xX
bx W
bx V
bx U
1T
xS
bx R
bx Q
bx P
bx O
xN
b0 M
1L
bx K
xJ
bx I
bx H
xG
xF
0E
xD
xC
bx B
bx A
1@
bx ?
bx >
bx =
bx <
bx ;
bx :
bx 9
bx 8
bx 7
bx 6
bx 5
bx 4
bx 3
b0 2
bx 1
bx00xx 0
bx /
bx .
b0 -
bx ,
bx +
bx *
bx )
bx (
bx '
bx &
bx00xx %
bx $
0#
0"
bx !
$end
#5
1#
#10
b0xx :
b0xx 6
b1 3
b1 +
b1 8
b1 ^
b1 ;
b1 ,
b1 4
b1 U
b1 7
0L
0@
0]
0T
1"
#20
b1 1
b1 6
b1 :
1N
0F
0G
b10 9
b10 5
0S
b1 &
b1 I
b1 _
b10 '
b10 H
b10 V
1D
b10 0
0e
0\
b1 P
b1 )
b1 =
b1 B
b1 .
b1 >
b1 K
b1 R
b10 *
b10 <
b10 A
b0 /
b0 ?
b0 O
b0 Q
b100000010 %
0C
0J
b0 $
b0 W
b0 `
b0 b
1a
b0 c
b0 Y
b11 !
b11 (
1X
b0 Z
1L
1@
1]
1T
0"
#25
0#
#30
0L
0@
0]
0T
1"
#40
b10 :
b10 6
b11 9
b11 5
1e
b111000010 %
1\
0a
b1 c
b0 !
b0 (
0X
b10 Z
1L
1@
1]
1T
0"
#50
b100 :
b100 6
b10 +
b10 8
b10 ^
b10 ;
b10 ,
b10 4
b10 U
b10 7
0L
0@
0]
0T
1"
#60
b1 b
b0xx $
b0xx W
b0xx `
b10 Y
b10 1
b1010 0
b111001010 %
1d
1L
1@
1]
1T
0"
#70
b10 6
b10 :
b100 M
b1000 -
b1000 2
b100 ,
b100 4
b100 U
b100 7
b100 +
b100 8
b100 ^
b100 ;
b10 3
0L
0@
0]
0T
1"
#80
b1 :
1F
b10 9
b0 &
b0 I
b0 _
0e
b0 )
b0 =
b0 B
b10 .
b10 >
b10 K
b10 R
b10 !
b10 (
1a
b0 c
b1 Z
b10 1
b100 M
b1000 -
b1000 2
b100010 0
b101100010 %
0d
1L
1@
1]
1T
0"
#90
b100 6
b10 P
b1 +
b1 8
b1 ^
b1 ;
b10 ,
b10 4
b10 U
b10 7
0L
0@
0]
0T
1"
#100
b11 .
b11 >
b11 K
b11 R
b0 b
b0xx $
b0xx W
b0xx `
b11 Y
b111 M
b1110 -
b1110 2
b100110 0
b101100110 %
1[
1L
1@
1]
1T
0"
#110
b10 6
b11 P
b100 ,
b100 4
b100 U
b100 7
0L
0@
0]
0T
1"
#120
b1 6
b10 5
b1 '
b1 H
b1 V
0\
b1 *
b1 <
b1 A
b100 /
b100 ?
b100 O
b100 Q
b101 .
b101 >
b101 K
b101 R
b11 !
b11 (
1X
b0 Z
b100 M
b1000 -
b1000 2
b100010 0
b100100010 %
0[
1L
1@
1]
1T
0"
#130
b101 P
b1 ,
b1 4
b1 U
b1 7
0L
0@
0]
0T
1"
#140
b1 1
b10 6
b0 M
b0 -
b0 2
b10 0
0F
b11 5
b1111111111111111 &
b1111111111111111 I
b1111111111111111 _
b101000010 %
1\
b1111111111111111 )
b1111111111111111 =
b1111111111111111 B
b110 .
b110 >
b110 K
b110 R
b0 $
b0 W
b0 `
b0 Y
b10 !
b10 (
0X
b1 Z
1L
1@
1]
1T
0"
#150
b100 6
b110 P
b10 ,
b10 4
b10 U
b10 7
b1 3
0L
0@
0]
0T
1"
#160
b10 :
b11 9
1e
b0 !
b0 (
0a
b1111111111111111 c
b0x $
b0x W
b0x `
b1 Y
b10 1
b110 0
b111000110 %
1[
1L
1@
1]
1T
0"
#170
b10 M
b100 :
b10 6
b100 -
b100 2
b10 3
b10 +
b10 8
b10 ^
b10 ;
b100 ,
b100 4
b100 U
b100 7
0L
0@
0]
0T
1"
#180
b1 6
b10 5
1S
b1111111111111111 '
b1111111111111111 H
b1111111111111111 V
0\
b1111111111111111 *
b1111111111111111 <
b1111111111111111 A
b111 /
b111 ?
b111 O
b111 Q
bx1 $
bx1 W
bx1 `
b1111111111111111 b
b1 !
b1 (
1X
b0 Z
b0 M
b1 1
b0 -
b0 2
b10 0
b110000010 %
0[
1L
1@
1]
1T
0"
#190
b10 :
b111 P
b1 ,
b1 4
b1 U
b1 7
b100 +
b100 8
b100 ^
b100 ;
b1 3
0L
0@
0]
0T
1"
#200
b10 6
b11 5
b111000010 %
1\
b1111111111111110 c
bx $
bx W
bx `
b0 Y
b0 !
b0 (
0X
b1111111111111111 Z
1L
1@
1]
1T
0"
#210
b100 :
b100 6
b10 +
b10 8
b10 ^
b10 ;
b10 ,
b10 4
b10 U
b10 7
0L
0@
0]
0T
1"
#220
b1111111111111101 b
b11111111111111x1 $
b11111111111111x1 W
b11111111111111x1 `
b1111111111111111 Y
1L
1@
1]
1T
0"
